LICENSE
MANIFEST.in
README.rst
setup.cfg
setup.py
versioneer.py
tpDcc/__init__.py
tpDcc/libs/__init__.py
tpDcc/libs/curves/__init__.py
tpDcc/libs/curves/__logging__.ini
tpDcc/libs/curves/__version__.py
tpDcc/libs/curves/_version.py
tpDcc/libs/curves/core/__init__.py
tpDcc/libs/curves/core/consts.py
tpDcc/libs/curves/core/curveslib.py
tpDcc/libs/curves/core/lib.py
tpDcc/libs/curves/dccs/__init__.py
tpDcc/libs/curves/dccs/max/__init__.py
tpDcc/libs/curves/dccs/max/curveslib.py
tpDcc/libs/curves/dccs/maya/__init__.py
tpDcc/libs/curves/dccs/maya/curveslib.py
tpDcc/libs/curves/dccs/maya/commands/__init__.py
tpDcc/libs/curves/dccs/maya/commands/createfromdata.py
tpDcc/libs/curves/dccs/maya/commands/createfrompath.py
tpDcc_libs_curves.egg-info/PKG-INFO
tpDcc_libs_curves.egg-info/SOURCES.txt
tpDcc_libs_curves.egg-info/dependency_links.txt
tpDcc_libs_curves.egg-info/not-zip-safe
tpDcc_libs_curves.egg-info/requires.txt
tpDcc_libs_curves.egg-info/top_level.txt