Metadata-Version: 2.1
Name: tpDcc-libs-curves
Version: 0.0.1
Summary: Library to manage curves in a DCC agnostic way
Home-page: https://github.com/tpDcc/tpDcc-libs-curves
Author: Tomas Poveda
Author-email: tpovedatd@gmail.com
License: MIT
Platform: UNKNOWN
Provides-Extra: dev
Provides-Extra: test
